simpsave/__init__.py
simpsave/core.py
simpsave-10.1.0.dist-info/METADATA
simpsave-10.1.0.dist-info/WHEEL
simpsave-10.1.0.dist-info/top_level.txt
simpsave-10.1.0.dist-info/RECORD
