Metadata-Version: 2.4
Name: simpsave
Version: 10.1.0
Summary: A lightweight Python library for persisting basic variables with multiple storage engines. Ideal for small-scale data storage with "read-and-use" capability.
Home-page: https://github.com/Water-Run/SimpSave
Author: WaterRun
Author-email: 2263633954@qq.com
License: MIT
Project-URL: Bug Tracker, https://github.com/Water-Run/SimpSave/issues
Project-URL: Documentation, https://github.com/Water-Run/SimpSave
Project-URL: Source Code, https://github.com/Water-Run/SimpSave
Keywords: persistence,storage,key-value,database,lightweight,simple
Classifier: Programming Language :: Python :: 3
Classifier: Programming Language :: Python :: 3.10
Classifier: Programming Language :: Python :: 3.11
Classifier: Programming Language :: Python :: 3.12
Classifier: License :: OSI Approved :: MIT License
Classifier: Operating System :: OS Independent
Classifier: Intended Audience :: Developers
Classifier: Topic :: Software Development :: Libraries :: Python Modules
Classifier: Topic :: Database
Classifier: Development Status :: 4 - Beta
Requires-Python: >=3.10
Provides-Extra: xml
Provides-Extra: ini
Provides-Extra: json
Provides-Extra: yml
Requires-Dist: PyYAML>=6.0; extra == "yml"
Provides-Extra: toml
Requires-Dist: tomli>=2.0.0; python_version < "3.11" and extra == "toml"
Requires-Dist: tomli-w>=1.0.0; extra == "toml"
Provides-Extra: sqlite
Provides-Extra: clean
Provides-Extra: basic
Requires-Dist: PyYAML>=6.0; extra == "basic"
Requires-Dist: tomli>=2.0.0; python_version < "3.11" and extra == "basic"
Requires-Dist: tomli-w>=1.0.0; extra == "basic"
Provides-Extra: full
Requires-Dist: PyYAML>=6.0; extra == "full"
Requires-Dist: tomli>=2.0.0; python_version < "3.11" and extra == "full"
Requires-Dist: tomli-w>=1.0.0; extra == "full"
Dynamic: author
Dynamic: author-email
Dynamic: classifier
Dynamic: description
Dynamic: description-content-type
Dynamic: home-page
Dynamic: keywords
Dynamic: license
Dynamic: project-url
Dynamic: provides-extra
Dynamic: requires-python
Dynamic: summary
